nifi_deploy/__init__.py
nifi_deploy/__main__.py
nifi_deploy/nifi.py
nifi_deploy/nifi_deploy.py
nifi_deploy-0.1.9.dist-info/DESCRIPTION.rst
nifi_deploy-0.1.9.dist-info/METADATA
nifi_deploy-0.1.9.dist-info/RECORD
nifi_deploy-0.1.9.dist-info/WHEEL
nifi_deploy-0.1.9.dist-info/entry_points.txt
nifi_deploy-0.1.9.dist-info/metadata.json
nifi_deploy-0.1.9.dist-info/top_level.txt
