Metadata-Version: 2.0
Name: nifi-deploy
Version: 0.1.9
Summary: Easy CLI tool for exporting and importing Nifi templates to and from XML files.
Home-page: https://pypi.org/project/nifi-deploy/
Author: Mads H. Jakobsen
Author-email: mads@hgaard.net
License: MIT
Keywords: nifi deploy template nipyapi cli automation
Platform: UNKNOWN
Classifier: Development Status :: 4 - Beta
Classifier: Environment :: Console
Classifier: Intended Audience :: Developers
Classifier: Intended Audience :: System Administrators
Classifier: License :: OSI Approved :: MIT License
Classifier: Natural Language :: English
Classifier: Operating System :: MacOS
Classifier: Operating System :: Microsoft :: Windows
Classifier: Operating System :: POSIX :: Linux
Classifier: Programming Language :: Python :: 3 :: Only
Classifier: Topic :: Software Development :: User Interfaces
Classifier: Topic :: System :: Archiving :: Packaging
Classifier: Topic :: System :: Systems Administration
Requires-Dist: nipyapi (==0.8.0)
Requires-Dist: requests (==2.18.4)
Requires-Dist: pyopenssl (==17.5.0)
